aiozabbix/__init__.py
aiozabbix/py.typed
aiozabbix/test_aiozabbix.py
aiozabbix-1.4.0.dist-info/licenses/LICENSE.txt
aiozabbix-1.4.0.dist-info/METADATA
aiozabbix-1.4.0.dist-info/WHEEL
aiozabbix-1.4.0.dist-info/top_level.txt
aiozabbix-1.4.0.dist-info/RECORD
