Metadata-Version: 2.4
Name: aiozabbix
Version: 1.4.0
Summary: Asynchronous Zabbix API Python interface
Author-email: Nicklas Lindgren <nili@modio.se>, "D.S. Ljungmark" <spider@modio.se>
License:                   GNU LESSER GENERAL PUBLIC LICENSE
Project-URL: Repository, https://gitlab.com/ModioAB/aiozabbix
Keywords: zabbix,monitoring,api
Classifier: Framework :: AsyncIO
Classifier: License :: OSI Approved :: GNU Lesser General Public License v2 or later (LGPLv2+)
Classifier: Programming Language :: Python
Classifier: Programming Language :: Python :: 3.6
Requires-Python: >=3.11
License-File: LICENSE.txt
Requires-Dist: aiohttp>=3.8.6
Requires-Dist: opentelemetry-api>=1.12.0
Requires-Dist: opentelemetry-semantic-conventions>=0.33b0
Dynamic: license-file
